{"Expediente:":"126851","R.U.C.:":"0992539445001","Fecha de constitución:":"2007-03-30","Nacionalidad:":"ECUADOR","Plazo social:":"2057-03-30","Oficina de control:":"GUAYAQUIL","Tipo de compañía:":"RESPONSABILIDAD LIMITADA","Situación legal:":"ACTIVA","Provincia:":"GUAYAS","Cantón:":"GUAYAQUIL","Ciudad:":"GUAYAQUIL","Parroquia:":"","Calle:":"Av. Juan Tanca Marengo","Número:":"10","Intersección:":"LOTIZACIÓN SANTA ADRIANA","Ciudadela:":"","Conjunto:":"LOTIZACIÓN SANTA ADRIANA Mz 2 S 10","Edificio/Centro comercial:":"","Barrio:":"TARQUI","Kilómetro:":"Km 6.5","Camino:":"","Piso:":"0","Bloque:":"","Referencia ubicación:":"FRENTE AL COLEGIO AMERICANO","Casillero postal:":"","Celular:":"0994493211","Teléfono 1:":"046008210","Teléfono 2:":"046008211","Sitio web:":"","Correo 1:":"legal@riasem.com.ec","Correo 2:":"gborja@riasem.com.ec","¿Es proveedora de bienes o servicios del Estado?:":"NO","¿Ofrece servicios de pagos a remesas?:":"NO","¿Compañía vende a crédito?:":"NO","¿Pertenece a MV?:":"NO","¿Es sociedad de interés público?:":"NO","¿Es una compañía BIC?:":"NO","Año desde que es una compañía BIC:":"NO APLICA","Areas impacto BIC:":"NO APLICA","Disposición judicial que afecta a la compañía:":"NINGUNA","Fecha última actualización societaria:":"2022-05-27 01:20:51","Objeto social:":"ARTICULO SEGUNDO: OBJETO SOCIAL.- TENDRA POR OBJETO DEDICARSE A LA EXPLOTACION DE LOS SERVICIOS DE TRANSPORTE AEREO, SERVICIOS DE TRABAJOS AEREOS, ESPECIALMENTE DE FUMIGACION AEREA Y ACTIVIDADES CONEXAS;.......................","CIIU actividad nivel 2:":"H51","Descripción:":"ALQUILER DE EQUIPO DE TRANSPORTE AÉREO CON OPERADORES PARA EL TRANSPORTE DE PASAJEROS, VUELOS CONTRATADOS (CHÁRTER) PARA PASAJEROS.","CIIU operación principal:":"H5110.03","Capital suscrito:":"16,000.00","Capital autorizado:":"0.00","Valor nominal acciones:":"1.0000"}