{"Expediente:":"167173","R.U.C.:":"0992796316001","Fecha de constitución:":"2013-01-07","Nacionalidad:":"ECUADOR","Plazo social:":"2063-01-07","Oficina de control:":"GUAYAQUIL","Tipo de compañía:":"ANÓNIMA","Situación legal:":"DISOLUC. Y LIQUIDAC. OFICIO INSC. EN RM","Provincia:":"GUAYAS","Cantón:":"GUAYAQUIL","Ciudad:":"GUAYAQUIL","Parroquia:":"","Calle:":"ALBERTO REINA","Número:":"205","Intersección:":"VILLAMIL - ELOY ALFARO","Ciudadela:":"","Conjunto:":"","Edificio/Centro comercial:":"ASOCIACION 28 DE SEPTEIMBRE PISO 1","Barrio:":"","Kilómetro:":"","Camino:":"","Piso:":"OF. 1","Bloque:":"","Referencia ubicación:":"ATRAS DEL EDIF. EL DORADO","Casillero postal:":"","Celular:":"0984166892","Teléfono 1:":"5000488","Teléfono 2:":"046002904","Sitio web:":"","Correo 1:":"celebriticorp@yahoo.com","Correo 2:":"abongu_sa@hotmail.com","¿Es proveedora de bienes o servicios del Estado?:":"NO","¿Ofrece servicios de pagos a remesas?:":"NO","¿Compañía vende a crédito?:":"NO","¿Pertenece a MV?:":"NO","¿Es sociedad de interés público?:":"NO","¿Es una compañía BIC?:":"NO","Año desde que es una compañía BIC:":"NO APLICA","Areas impacto BIC:":"NO APLICA","Disposición judicial que afecta a la compañía:":"NINGUNA","Fecha última actualización societaria:":"2013-09-05 16:11:45","Objeto social:":"ARTICULO TERCERO: El objeto social de la compañía es dedicarse a: ...Diecisiete.uno) Importación, comercialización, compra, venta al por mayor y menor de discos compactos CD; ...","CIIU actividad nivel 2:":"G46","Descripción:":"VENTA AL POR MAYOR DE CINTAS Y DISQUETES Y DISCOS MAGNÉTICOS Y ÓPTICOS (CD, DVD) DE SONIDO Y DE VÍDEO NO GRABADAS.","CIIU operación principal:":"G4652.03","Capital suscrito:":"800.00","Capital autorizado:":"1,600.00","Valor nominal acciones:":"1.0000"}