{"Expediente:":"736225","R.U.C.:":"0993323063001","Fecha de constitución:":"2021-04-13","Nacionalidad:":"ECUADOR","Plazo social:":"INDEFINIDO","Oficina de control:":"GUAYAQUIL","Tipo de compañía:":"SOCIEDAD POR ACCIONES SIMPLIFICADA","Situación legal:":"ACTIVA","Provincia:":"GUAYAS","Cantón:":"GUAYAQUIL","Ciudad:":"GUAYAQUIL","Parroquia:":"","Calle:":"Samanes","Número:":"5","Intersección:":"Samanes","Ciudadela:":"","Conjunto:":"","Edificio/Centro comercial:":"","Barrio:":"","Kilómetro:":"","Camino:":"","Piso:":"","Bloque:":"","Referencia ubicación:":"Samanes 1 manzana 120 solar 5","Casillero postal:":"","Celular:":"0990384641","Teléfono 1:":"2242526","Teléfono 2:":"","Sitio web:":"","Correo 1:":"dj2unik@gmail.com","Correo 2:":"jormar7602@hotmail.com","¿Es proveedora de bienes o servicios del Estado?:":"NO","¿Ofrece servicios de pagos a remesas?:":"NO","¿Compañía vende a crédito?:":"NO","¿Pertenece a MV?:":"NO","¿Es sociedad de interés público?:":"NO","¿Es una compañía BIC?:":"NO","Año desde que es una compañía BIC:":"NO APLICA","Areas impacto BIC:":"NO APLICA","Disposición judicial que afecta a la compañía:":"NINGUNA","Fecha última actualización societaria:":"2021-05-01 13:26:08","Objeto social:":"Y CUALQUIER ACTIVIDAD MERCANTIL O CIVIL, LICITA","CIIU actividad nivel 2:":"F41","Descripción:":"CONSTRUCCIÓN DE TODO TIPO DE EDIFICIOS RESIDENCIALES: CASAS FAMILIARES INDIVIDUALES, EDIFICIOS MULTIFAMILIARES, INCLUSO EDIFICIOS DE ALTURAS ELEVADAS, VIVIENDAS PARA ANCIANATOS, CASAS PARA BENEFICENCIA, ORFANATOS, CÁRCELES, CUARTELES, CONVENTOS, CASAS RELIGIOSAS. INCLUYE REMODELACIÓN, RENOVACIÓN O REHABILITACIÓN DE ESTRUCTURAS EXISTENTES.","CIIU operación principal:":"F4100.10","Capital suscrito:":"800.00","Capital autorizado:":"0.00","Valor nominal acciones:":"1.0000"}