{"Expediente:":"202361","R.U.C.:":"0190369633001","Fecha de constitución:":"2009-12-16","Nacionalidad:":"ECUADOR","Plazo social:":"2059-12-16","Oficina de control:":"CUENCA","Tipo de compañía:":"ANÓNIMA","Situación legal:":"ACTIVA","Provincia:":"AZUAY","Cantón:":"CUENCA","Ciudad:":"CUENCA","Parroquia:":"","Calle:":"GRAN COLOMBIA","Número:":"7-87","Intersección:":"LUIS CORDERO","Ciudadela:":"","Conjunto:":"","Edificio/Centro comercial:":"TORRE DE NEGOCIOS EL DORADO","Barrio:":"EL SAGRARIO","Kilómetro:":"","Camino:":"","Piso:":"4TO","Bloque:":"","Referencia ubicación:":"JUNTO JOYERIA GUILLERMO VAZQUEZ","Casillero postal:":"","Celular:":"0998070708","Teléfono 1:":"072826293","Teléfono 2:":"072847390","Sitio web:":"","Correo 1:":"mcrespo@gvazquez.com.ec","Correo 2:":"mcrespo_vaz@hotmail.com","¿Es proveedora de bienes o servicios del Estado?:":"NO","¿Ofrece servicios de pagos a remesas?:":"NO","¿Compañía vende a crédito?:":"NO","¿Pertenece a MV?:":"NO","¿Es sociedad de interés público?:":"NO","¿Es una compañía BIC?:":"NO","Año desde que es una compañía BIC:":"NO APLICA","Areas impacto BIC:":"NO APLICA","Disposición judicial que afecta a la compañía:":"NINGUNA","Fecha última actualización societaria:":"2022-06-07 15:13:24","Objeto social:":"La tenencia de acciones o participaciones de otras empresas. En general, podrá realizar toda clase de actos o contratos que se requieran o convengan para el cumplimiento de su objeto social.","CIIU actividad nivel 2:":"K64","Descripción:":"ACTIVIDADES DE SOCIEDADES DE CARTERA, ES DECIR, UNIDADES TENEDORAS DE ACTIVOS DE UN GRUPO DE EMPRESAS FILIALES (CON PARTICIPACIÓN DE CONTROL EN SU CAPITAL SOCIAL) Y CUYA ACTIVIDAD PRINCIPAL CONSISTE EN LA PROPIEDAD DEL GRUPO. LAS SOCIEDADES DE CARTERA CLASIFICADAS EN ESTA CLASE NO SUMINISTRAN NINGÚN OTRO SERVICIO A LAS EMPRESAS PARTICIPADAS, ES DECIR, NO ADMINISTRAN NI GESTIONAN OTRAS UNIDADES.","CIIU operación principal:":"K6420.00","Capital suscrito:":"1,000.00","Capital autorizado:":"","Valor nominal acciones:":"1.0000"}