{"Expediente:":"306598","R.U.C.:":"0993020745001","Fecha de constitución:":"2017-04-03","Nacionalidad:":"ECUADOR","Plazo social:":"2067-04-03","Oficina de control:":"GUAYAQUIL","Tipo de compañía:":"ANÓNIMA","Situación legal:":"ACTIVA","Provincia:":"GUAYAS","Cantón:":"GUAYAQUIL","Ciudad:":"GUAYAQUIL","Parroquia:":"","Calle:":"CIRCUNVALACION SUR","Número:":"919B","Intersección:":"ILANES","Ciudadela:":"","Conjunto:":"","Edificio/Centro comercial:":"","Barrio:":"","Kilómetro:":"","Camino:":"","Piso:":"","Bloque:":"","Referencia ubicación:":"EN URDESA","Casillero postal:":"","Celular:":"0987841862","Teléfono 1:":"045018673","Teléfono 2:":"045018673","Sitio web:":"","Correo 1:":"callcenter@ecuadental.com","Correo 2:":"bjpereza10@hotmail.com","¿Es proveedora de bienes o servicios del Estado?:":"NO","¿Ofrece servicios de pagos a remesas?:":"NO","¿Compañía vende a crédito?:":"NO","¿Pertenece a MV?:":"NO","¿Es sociedad de interés público?:":"NO","¿Es una compañía BIC?:":"NO","Año desde que es una compañía BIC:":"NO APLICA","Areas impacto BIC:":"NO APLICA","Disposición judicial que afecta a la compañía:":"NINGUNA","Fecha última actualización societaria:":"2017-06-19 09:55:02","Objeto social:":"ACTIVIDADES DE PROGRAMACIÓN INFORMATICA Y ACTIVIDADES CONEXAS","CIIU actividad nivel 2:":"J62","Descripción:":"ACTIVIDADES DE PLANIFICACIÓN Y DISEÑO DE SISTEMAS INFORMÁTICOS QUE INTEGRAN EQUIPO Y PROGRAMAS INFORMÁTICOS Y TECNOLOGÍA DE LAS COMUNICACIONES.","CIIU operación principal:":"J6202.10","Capital suscrito:":"800.00","Capital autorizado:":"1,600.00","Valor nominal acciones:":"1.0000"}