{"Expediente:":"307254","R.U.C.:":"0993032565001","Fecha de constitución:":"2017-06-19","Nacionalidad:":"ECUADOR","Plazo social:":"2067-06-19","Oficina de control:":"GUAYAQUIL","Tipo de compañía:":"RESPONSABILIDAD LIMITADA","Situación legal:":"ACTIVA","Provincia:":"GUAYAS","Cantón:":"GUAYAQUIL","Ciudad:":"GUAYAQUIL","Parroquia:":"","Calle:":"ALBORADA 11VA ETAPA","Número:":"MZ. 8 V. 1","Intersección:":"7MA Y 6TO CALLEJON","Ciudadela:":"ALBORADA ONCEAVA ETAPA","Conjunto:":"CASA DE DOS PISOS","Edificio/Centro comercial:":"CASA DE DOS PISOS","Barrio:":"ALBORADA","Kilómetro:":"0","Camino:":"ATRAS DE LA OFICINA DE LA JOYA","Piso:":"1","Bloque:":"","Referencia ubicación:":"FRENTE A  FYBECA DE LA ALBORADA QUEDA LA","Casillero postal:":"","Celular:":"0986348808","Teléfono 1:":"042177689","Teléfono 2:":"042177689","Sitio web:":"","Correo 1:":"leito_79@hotmail.com","Correo 2:":"juangarciaestrella@hotmail.com","¿Es proveedora de bienes o servicios del Estado?:":"NO","¿Ofrece servicios de pagos a remesas?:":"NO","¿Compañía vende a crédito?:":"NO","¿Pertenece a MV?:":"NO","¿Es sociedad de interés público?:":"NO","¿Es una compañía BIC?:":"NO","Año desde que es una compañía BIC:":"NO APLICA","Areas impacto BIC:":"NO APLICA","Disposición judicial que afecta a la compañía:":"NINGUNA","Fecha última actualización societaria:":"2022-05-17 13:56:12","Objeto social:":"La compañía tendrá por objeto dedicarse a las operaciones comprendidas dentro del Nivel 2 del CIIU: P85 - ENSEÑANZA; así como también podrá comprender las etapas o fases de CAPACITACIÓN, ASESORAMIENTO  de la actividad antes mencionada. Para cumplir con el objeto social descrito en el presente Estatuto Social, la compañía podrá ejecutar actos y contratos conforme a las Leyes Ecuatorianas y que tengan relación con el mismo.","CIIU actividad nivel 2:":"P85","Descripción:":"ACTIVIDADES DE SERVICIOS DE  DEBERES DIRIGIDOS, TUTORÍA ACADÉMICA, PREPARACIÓN PARA EL INGRESO A LA UNIVERSIDAD, CENTROS DE ENSEÑANZA QUE OFRECEN CURSOS DE RECUPERACIÓN Y CURSOS DE REPASO PARA EXÁMENES PROFESIONALES.","CIIU operación principal:":"P8549.12","Capital suscrito:":"400.00","Capital autorizado:":"0.00","Valor nominal acciones:":"200.0000"}