{"Expediente:":"120540","R.U.C.:":"0992416408001","Fecha de constitución:":"2005-08-09","Nacionalidad:":"BRASIL","Plazo social:":"INDEFINIDO","Oficina de control:":"GUAYAQUIL","Tipo de compañía:":"SUCURSAL  EXTRANJERA","Situación legal:":"ACTIVA","Provincia:":"GUAYAS","Cantón:":"GUAYAQUIL","Ciudad:":"GUAYAQUIL","Parroquia:":"","Calle:":"AV. FRANCISCO DE ORELLANA","Número:":"1","Intersección:":"VICTOR HUGO SICOURET","Ciudadela:":"KENNEDY NORTE","Conjunto:":"","Edificio/Centro comercial:":"LAS CAMARAS","Barrio:":"","Kilómetro:":"","Camino:":"","Piso:":"1","Bloque:":"TORRE A","Referencia ubicación:":"JUNTO AL HOTEL HILTON COLON","Casillero postal:":"","Celular:":"0998948106","Teléfono 1:":"022992300","Teléfono 2:":"022992300","Sitio web:":"","Correo 1:":"jorge.salazaru@latam.com","Correo 2:":"wilson.carranza@latam.com","¿Es proveedora de bienes o servicios del Estado?:":"NO","¿Ofrece servicios de pagos a remesas?:":"NO","¿Compañía vende a crédito?:":"NO","¿Pertenece a MV?:":"NO","¿Es sociedad de interés público?:":"NO","¿Es una compañía BIC?:":"NO","Año desde que es una compañía BIC:":"NO APLICA","Areas impacto BIC:":"NO APLICA","Disposición judicial que afecta a la compañía:":"NINGUNA","Fecha última actualización societaria:":"2020-12-04 12:03:26","Objeto social:":"actividades de transporte aéreo no regular de carga internacional","CIIU actividad nivel 2:":"H51","Descripción:":"TRANSPORTE AÉREO DE CARGA CON ITINERARIOS Y HORARIOS ESTABLECIDOS.","CIIU operación principal:":"H5120.01","Capital suscrito:":"16,000.00","Capital autorizado:":"","Valor nominal acciones:":"0.0000"}