{"Expediente:":"126156","R.U.C.:":"0992500379001","Fecha de constitución:":"2007-01-23","Nacionalidad:":"ECUADOR","Plazo social:":"2057-01-23","Oficina de control:":"GUAYAQUIL","Tipo de compañía:":"ANÓNIMA","Situación legal:":"ACTIVA","Provincia:":"GUAYAS","Cantón:":"GUAYAQUIL","Ciudad:":"GUAYAQUIL","Parroquia:":"","Calle:":"AV. RODRIGO CHAVEZ","Número:":"LOCAL 4","Intersección:":"CIUDAD COLON","Ciudadela:":"URDESA NORTE","Conjunto:":"","Edificio/Centro comercial:":"","Barrio:":"","Kilómetro:":"","Camino:":"","Piso:":"","Bloque:":"EMPRESARIAL 10","Referencia ubicación:":"PARQUE EMPRESARIAL COLON","Casillero postal:":"","Celular:":"0986696431","Teléfono 1:":"042136174","Teléfono 2:":"042136174","Sitio web:":"www.1700digital.com","Correo 1:":"jaimemicontador2010@gmail.com","Correo 2:":"evelynhernandez1094@gmail.com","¿Es proveedora de bienes o servicios del Estado?:":"NO","¿Ofrece servicios de pagos a remesas?:":"NO","¿Compañía vende a crédito?:":"NO","¿Pertenece a MV?:":"NO","¿Es sociedad de interés público?:":"NO","¿Es una compañía BIC?:":"NO","Año desde que es una compañía BIC:":"NO APLICA","Areas impacto BIC:":"NO APLICA","Disposición judicial que afecta a la compañía:":"NINGUNA","Fecha última actualización societaria:":"2022-05-01 00:59:36","Objeto social:":"LA COMPAÑIA SE DEDICARA A LA COMERCIALIZACION DE MEDIOS Y PRODUCTOS DIGITALES O AFINES, SU MERCADEO, PUBLICIDAD, INVESTIGACION, DISEÑO, PRODUCCION, CAPACITACION EN O PARA SU USO...COMPRA VENTA DE MAQUINAS DE COMPUTACIÓN.. ETC","CIIU actividad nivel 2:":"G46","Descripción:":"VENTA AL POR MAYOR DE COMPUTADORAS Y EQUIPO PERIFÉRICO.","CIIU operación principal:":"G4651.01","Capital suscrito:":"800.00","Capital autorizado:":"1,600.00","Valor nominal acciones:":"1.0000"}