{"Expediente:":"720070","R.U.C.:":"1792915430001","Fecha de constitución:":"2018-10-02","Nacionalidad:":"ECUADOR","Plazo social:":"2068-10-02","Oficina de control:":"QUITO","Tipo de compañía:":"RESPONSABILIDAD LIMITADA","Situación legal:":"ACTIVA","Provincia:":"PICHINCHA","Cantón:":"CAYAMBE","Ciudad:":"CAYAMBE","Parroquia:":"","Calle:":"10 DE AGOSTO","Número:":"S/N","Intersección:":"HUMBERTO FIERRO","Ciudadela:":"","Conjunto:":"","Edificio/Centro comercial:":"","Barrio:":"","Kilómetro:":"","Camino:":"","Piso:":"","Bloque:":"","Referencia ubicación:":"DIAGONAL A PINTULAC","Casillero postal:":"","Celular:":"0960591457","Teléfono 1:":"022111170","Teléfono 2:":"022111170","Sitio web:":"","Correo 1:":"jcf1684@gmail.com","Correo 2:":"jefecontabilidad@360grupoconsultor.com","¿Es proveedora de bienes o servicios del Estado?:":"NO","¿Ofrece servicios de pagos a remesas?:":"NO","¿Compañía vende a crédito?:":"NO","¿Pertenece a MV?:":"NO","¿Es sociedad de interés público?:":"NO","¿Es una compañía BIC?:":"NO","Año desde que es una compañía BIC:":"NO APLICA","Areas impacto BIC:":"NO APLICA","Disposición judicial que afecta a la compañía:":"NINGUNA","Fecha última actualización societaria:":"2022-05-12 10:30:03","Objeto social:":"LA COMPAÑÍA TENDRÁ COMO OBJETO SOCIAL PRINCIPAL LA PRESTACIÓN DE SERVICIOS PROFESIONALES DE CONSULTORÍA ESPECIALIZADOS EN ADMINISTRACIÓN DE EMPRESAS, AUDITORIA, CONTABILIDAD Y TRIBUTACIÓN QUE TENGAN POR OBJETO IDENTIFICAR, PLANIFICAR, ELABORAR O EVALUAR PROYECTOS DE DESARROLLO EN SUS NIVELES DE PREFACTIBILIDAD, FACTIBILIDAD, DISEÑO U OPERACIÓN, LA VENTA Y COMERCIALIZACIÓN DE SOFTWARE RELACIONADOS AL OBJETO DE LA COMPAÑÍA; Y LA CAPACITACIÓN SOBRE TEMAS RELACIONADOS A SU OBJETO SOCIAL.","CIIU actividad nivel 2:":"M69","Descripción:":"OTRAS ACTIVIDADES DE CONTABILIDAD, TENEDURÍA DE LIBROS Y AUDITORIA; CONSULTORÍA FISCAL (PROCESAMIENTO DE NÓMINA, ETCÉTERA).","CIIU operación principal:":"M6920.09","Capital suscrito:":"1,000.00","Capital autorizado:":"0.00","Valor nominal acciones:":"1.0000"}