{"Expediente:":"720162","R.U.C.:":"1792915031001","Fecha de constitución:":"2018-08-30","Nacionalidad:":"ECUADOR","Plazo social:":"2118-08-30","Oficina de control:":"QUITO","Tipo de compañía:":"ANÓNIMA","Situación legal:":"ACTIVA","Provincia:":"PICHINCHA","Cantón:":"QUITO","Ciudad:":"QUITO","Parroquia:":"","Calle:":"DE LAS HIGUERAS","Número:":"E15-34","Intersección:":"DE LAS ALONDRAS","Ciudadela:":"","Conjunto:":"","Edificio/Centro comercial:":"","Barrio:":"MONTESERRÍN","Kilómetro:":"","Camino:":"","Piso:":"","Bloque:":"","Referencia ubicación:":"FRENTE A SANTILLANA","Casillero postal:":"170503","Celular:":"0987756467","Teléfono 1:":"0987756467","Teléfono 2:":"022223871","Sitio web:":"","Correo 1:":"mcastillo@1001carros.com","Correo 2:":"fgbaca@casabaca.com","¿Es proveedora de bienes o servicios del Estado?:":"NO","¿Ofrece servicios de pagos a remesas?:":"NO","¿Compañía vende a crédito?:":"NO","¿Pertenece a MV?:":"NO","¿Es sociedad de interés público?:":"NO","¿Es una compañía BIC?:":"NO","Año desde que es una compañía BIC:":"NO APLICA","Areas impacto BIC:":"NO APLICA","Disposición judicial que afecta a la compañía:":"NINGUNA","Fecha última actualización societaria:":"2020-12-17 15:47:17","Objeto social:":"LA COMPAÑÍA OPERARÁ Y SE DEDICARÁ A LO SIGUIENTE: INSTALACIÓN DE TALLERES PARA EL MANTENIMIENTO Y REPARACIÓN DE VEHÍCULOS AUTOMOTORES, ASÍ COMO TAMBIÉN LA COMPRAVENTA DE PARTES, PIEZAS, LUBRICANTES, REPUESTOS Y ACCESORIOS, EN GENERAL, PODRÁ CELEBRAR TODA CLASE DE ACTOS Y/O CONTRATOS AFINES O CONEXOS CON SU OBJETO Y PERMITIDOS POR LA LEY.","CIIU actividad nivel 2:":"G45","Descripción:":"MANTENIMIENTO Y REPARACIÓN DE VEHÍCULOS AUTOMOTORES: REPARACIÓN MECÁNICA, ELÉCTRICA, SISTEMAS DE INYECCIÓN ELÉCTRICOS, CARROCERÍAS, PARTES DE VEHÍCULOS AUTOMOTORES: PARABRISAS, VENTANAS, ASIENTOS Y TAPICERÍAS. INCLUYE EL TRATAMIENTO ANTI ÓXIDO, PINTURAS A PISTOLA O BROCHA A LOS VEHÍCULOS Y AUTOMOTORES, LA INSTALACIÓN DE PARTES, PIEZAS Y ACCESORIOS QUE NO SE REALIZA COMO PARTE DEL PROCESO DE FABRICACIÓN (PARLANTES, RADIOS, ALARMAS, ETCÉTERA).","CIIU operación principal:":"G4520.01","Capital suscrito:":"10,000.00","Capital autorizado:":"20,000.00","Valor nominal acciones:":"1.0000"}